<?xml version="1.0" encoding="UTF-8"?>

<odoo>
    <data noupdate="1">

        <record id="model_x_website_snippet" model="ir.model">
            <field name="name">x_website_snippet</field>
            <field name="model">x_website_snippet</field>
            <field name="state">manual</field>
        </record>

        <record id="field_x_name" model="ir.model.fields">
            <field name="name">x_name</field>
            <field name="field_description">Name</field>
            <field name="ttype">char</field>
            <field name="state">manual</field>
            <field name="required" eval="1"/>
            <field name="model_id" ref="model_x_website_snippet"/>
        </record>

        <record id="field_x_html" model="ir.model.fields">
            <field name="name">x_html</field>
            <field name="field_description">HTML</field>
            <field name="ttype">text</field>
            <field name="state">manual</field>
            <field name="required" eval="1"/>
            <field name="model_id" ref="model_x_website_snippet"/>
        </record>

        <record id="field_x_css" model="ir.model.fields">
            <field name="name">x_css</field>
            <field name="field_description">CSS</field>
            <field name="ttype">text</field>
            <field name="state">manual</field>
            <field name="required" eval="0"/>
            <field name="model_id" ref="model_x_website_snippet"/>
        </record>

        <record id="field_x_js" model="ir.model.fields">
            <field name="name">x_js</field>
            <field name="field_description">JavaScript</field>
            <field name="ttype">text</field>
            <field name="state">manual</field>
            <field name="required" eval="0"/>
            <field name="model_id" ref="model_x_website_snippet"/>
        </record>

    </data>

</odoo>